{
  "Name": "Viva Salon & Spa",
  "HyperLinkTell": "tel:(757)4167919",
  "TextTell": "(757)-416-7919",
  "GooglePlus": "https://www.google.com/search?q=Viva+Salon+Spa+23505",
  "Address": "7525 Tidewater Dr Unit 9, Norfolk, VA 23505",
  "LinkGoogleMapAddress": "https://maps.app.goo.gl/QZFRhpaYruZTAoFx7",
  "LinkIFrameGoogleMap": "https://www.google.com/maps/embed?pb=!1m14!1m8!1m3!1d12760.109092976305!2d-76.2563528!3d36.9136123!3m2!1i1024!2i768!4f13.1!3m3!1m2!1s0x89ba974efe560af3%3A0x3f049fa4c4ba8fa5!2sViva%20Salon%20%26%20Spa%20(15%25%20OFF%20New%20Customers%20-%20Must%20show%20coupon%20at%20check%20out)!5e0!3m2!1sen!2s!4v1725207711860!5m2!1sen!2s",
  "LinkBookingAppointment": "",
  "ShowCoupon": true,
  "Coupons": [
    {
      "Status": true,
      "Src": "/Content/images/popup/coupon-01.jpg"
    },
    {
      "Status": true,
      "Src": "/Content/images/popup/coupon-02.jpg"
    }
  ],
  "Prices": [],
  "Telegram": {
    "Title": "Telegram",
    "Url": "",
    "Position": 1,
    "ClassIcon": "fa fa-telegram",
    "BackgroundColor": "#34a9e4"
  },
  "Facebook": {
    "Title": "Facebook",
    "Url": "",
    "Position": 2,
    "ClassIcon": "fa fa-facebook-f",
    "BackgroundColor": "#1877f2"
  },
  "Instagram": {
    "Title": "Instagram",
    "Url": "",
    "Position": 3,
    "ClassIcon": "fa fa-instagram",
    "BackgroundColor": "radial-gradient(circle at 30% 107%, #fdf497 0%, #fdf497 5%, #fd5949 45%,#d6249f 60%,#285AEB 90%)"
  },
  "Twitter": {
    "Title": "Twitter",
    "Url": "",
    "Position": 4,
    "ClassIcon": "fa fa-twitter",
    "BackgroundColor": "#1d9bf0"
  },
  "Youtube": {
    "Title": "Youtube",
    "Url": "",
    "Position": 5,
    "ClassIcon": "fa fa-youtube-play",
    "BackgroundColor": "#ff0000"
  }
}
