{
  "Name": "Top Coat Nails Spa",
  "HyperLinkTell": "tel:(707)4471020",
  "TextTell": "(707)-447-1020",
  "GooglePlus": "https://www.google.com/search?q=Top+Coat+Nail+Salon+95688",
  "Address": "1631 E Monte Vista Ave #105, Vacaville, CA 95688",
  "LinkGoogleMapAddress": "https://maps.app.goo.gl/dv699ZHbannjangr7",
  "LinkIFrameGoogleMap": "https://www.google.com/maps/embed?pb=!1m14!1m8!1m3!1d12512.69187450072!2d-121.9635525!3d38.3681199!3m2!1i1024!2i768!4f13.1!3m3!1m2!1s0x80853d332dbcf903%3A0x90702668ce032003!2s(%245%20OFF%20Pedicures)%20Top%20Coat%20Nails%20Spa!5e0!3m2!1sen!2s!4v1717002466797!5m2!1sen!2s",
  "LinkBookingAppointment": "",
  "ShowCoupon": true,
  "Coupons": [],
  "Prices": [],
  "Telegram": {
    "Title": "Telegram",
    "Url": "",
    "Position": 1,
    "ClassIcon": "fa fa-telegram",
    "BackgroundColor": "#34a9e4"
  },
  "Facebook": {
    "Title": "Facebook",
    "Url": "https://www.facebook.com/profile.php?id=100083080911446",
    "Position": 2,
    "ClassIcon": "fa fa-facebook-f",
    "BackgroundColor": "#1877f2"
  },
  "Instagram": {
    "Title": "Instagram",
    "Url": "https://www.instagram.com/topcoatnailsinvacaville/",
    "Position": 3,
    "ClassIcon": "fa fa-instagram",
    "BackgroundColor": "radial-gradient(circle at 30% 107%, #fdf497 0%, #fdf497 5%, #fd5949 45%,#d6249f 60%,#285AEB 90%)"
  },
  "Twitter": {
    "Title": "Twitter",
    "Url": "",
    "Position": 4,
    "ClassIcon": "fa fa-twitter",
    "BackgroundColor": "#1d9bf0"
  },
  "Youtube": {
    "Title": "Youtube",
    "Url": "",
    "Position": 5,
    "ClassIcon": "fa fa-youtube-play",
    "BackgroundColor": "#ff0000"
  }
}
